validator/schema_validation.json
wkfs_wrapper/APIHandler.py
wkfs_wrapper/Utils.py
wkfs_wrapper/WKFSAdapter.py
wkfs_wrapper/constants.py
wkfs_wrapper/schema_validator.py
wkfs_wrapper-0.3.8.dist-info/LICENSE
wkfs_wrapper-0.3.8.dist-info/WHEEL
wkfs_wrapper-0.3.8.dist-info/METADATA
wkfs_wrapper-0.3.8.dist-info/RECORD
